MANIFEST.in
README.rst
requirements.txt
setup.py
rqalpha_mod_sentry/VERSION.txt
rqalpha_mod_sentry/__init__.py
rqalpha_mod_sentry/mod.py
rqalpha_mod_sentry.egg-info/PKG-INFO
rqalpha_mod_sentry.egg-info/SOURCES.txt
rqalpha_mod_sentry.egg-info/dependency_links.txt
rqalpha_mod_sentry.egg-info/not-zip-safe
rqalpha_mod_sentry.egg-info/requires.txt
rqalpha_mod_sentry.egg-info/top_level.txt