Metadata-Version: 1.1
Name: rqalpha-mod-sentry
Version: 0.1.0
Summary: A mod for RQAlpha Tracking error with Sentry
Home-page: https://github.com/ricequant/rqalpha-mod-sentry
Author: ricequant
Author-email: public@ricequant.com
License: Apache License v2
Platform: UNKNOWN
Classifier: Programming Language :: Python
Classifier: Operating System :: Microsoft :: Windows
Classifier: Operating System :: Unix
Classifier: Programming Language :: Python :: 2.7
Classifier: Programming Language :: Python :: 3.4
Classifier: Programming Language :: Python :: 3.5
Classifier: Programming Language :: Python :: 3.6
